MagsToolCommand/__init__.py
MagsToolCommand/run.py
MagsToolCommand-0.0.6.dist-info/LICENSE
MagsToolCommand-0.0.6.dist-info/METADATA
MagsToolCommand-0.0.6.dist-info/WHEEL
MagsToolCommand-0.0.6.dist-info/entry_points.txt
MagsToolCommand-0.0.6.dist-info/top_level.txt
MagsToolCommand-0.0.6.dist-info/RECORD
