Metadata-Version: 2.1
Name: MagsToolCommand
Version: 0.0.6
Summary: Hikesiya
Author: Hikesiya
Author-email: hien240891@gmail.com
Classifier: Programming Language :: Python :: 3
Classifier: License :: OSI Approved :: MIT License
Classifier: Operating System :: OS Independent
Requires-Python: >=3.7
License-File: LICENSE
Requires-Dist: click
